lycee/__init__.py
lycee/lycee.py
lycee-2.6.1.dist-info/METADATA
lycee-2.6.1.dist-info/RECORD
lycee-2.6.1.dist-info/WHEEL
lycee-2.6.1.dist-info/top_level.txt
