Metadata-Version: 2.1
Name: lycee
Version: 2.6.1
Summary: Un ensemble de fonctions pour utiliser facilement Python au lycée.
Home-page: http://edupython.tuxfamily.org/
Author: Vincent MAILLE
Author-email: vincent.maille@ac-amiens.fr
License: UNKNOWN
Platform: UNKNOWN
Classifier: Programming Language :: Python :: 3
Classifier: License :: CeCILL-B Free Software License Agreement (CECILL-B)
Classifier: Operating System :: OS Independent
Requires-Dist: numpy
Requires-Dist: scipy
Requires-Dist: matplotlib
